Metadata-Version: 2.1
Name: wordsapi
Version: 1.0.5
Summary: Python client library for Words API
Home-page: https://apimatic.io
Author: Muhammad Sufyan
Author-email: muhammad.sufyan@apimatic.io
License-File: LICENSE
Requires-Dist: jsonpickle (>=1.4.1,~=1.4)
Requires-Dist: requests (~=2.25)
Requires-Dist: cachecontrol (~=0.12.6)
Requires-Dist: python-dateutil (~=2.8.1)
Requires-Dist: enum34 (>=1.1.10,~=1.1)
